{
    "lat": 3.033,
    "lon": 101.45,
    "timezone": "Asia/Kuala_Lumpur",
    "timezone_offset": 28800,
    "data": [
        {
            "dt": 1709485200,
            "sunrise": 1709508245,
            "sunset": 1709551684,
            "temp": 26.67,
            "feels_like": 30.15,
            "pressure": 1011,
            "humidity": 94,
            "dew_point": 25.62,
            "clouds": 100,
            "wind_speed": 1.82,
            "wind_deg": 86,
            "weather": [
                {
                    "id": 501,
                    "main": "Rain",
                    "description": "moderate rain",
                    "icon": "10n"
                }
            ],
            "rain": {
                "1h": 3.41
            }
        }
    ]
}