{
    "lat": 3.033,
    "lon": 101.45,
    "timezone": "Asia/Kuala_Lumpur",
    "timezone_offset": 28800,
    "data": [
        {
            "dt": 1718240400,
            "sunrise": 1718233531,
            "sunset": 1718277791,
            "temp": 27.97,
            "feels_like": 31.72,
            "pressure": 1013,
            "humidity": 78,
            "dew_point": 23.77,
            "clouds": 20,
            "visibility": 10000,
            "wind_speed": 1.54,
            "wind_deg": 360,
            "weather": [
                {
                    "id": 801,
                    "main": "Clouds",
                    "description": "few clouds",
                    "icon": "02d"
                }
            ]
        }
    ]
}