{
    "lat": 3.033,
    "lon": 101.45,
    "timezone": "Asia/Kuala_Lumpur",
    "timezone_offset": 28800,
    "data": [
        {
            "dt": 1695610800,
            "sunrise": 1695596576,
            "sunset": 1695640159,
            "temp": 26.22,
            "feels_like": 26.22,
            "pressure": 1013,
            "humidity": 83,
            "dew_point": 23.1,
            "clouds": 20,
            "visibility": 10000,
            "wind_speed": 1.54,
            "wind_deg": 120,
            "weather": [
                {
                    "id": 500,
                    "main": "Rain",
                    "description": "light rain",
                    "icon": "10d"
                }
            ],
            "rain": {
                "1h": 0.21
            }
        }
    ]
}