{
    "lat": 3.033,
    "lon": 101.45,
    "timezone": "Asia/Kuala_Lumpur",
    "timezone_offset": 28800,
    "data": [
        {
            "dt": 1734843600,
            "sunrise": 1734822864,
            "sunset": 1734865867,
            "temp": 29.93,
            "feels_like": 36.9,
            "pressure": 1010,
            "humidity": 78,
            "dew_point": 25.67,
            "clouds": 96,
            "wind_speed": 2.29,
            "wind_deg": 214,
            "weather": [
                {
                    "id": 804,
                    "main": "Clouds",
                    "description": "overcast clouds",
                    "icon": "04d"
                }
            ]
        }
    ]
}