{
    "lat": 3.033,
    "lon": 101.45,
    "timezone": "Asia/Kuala_Lumpur",
    "timezone_offset": 28800,
    "data": [
        {
            "dt": 1738486800,
            "sunrise": 1738452483,
            "sunset": 1738495659,
            "temp": 30.61,
            "feels_like": 35.5,
            "pressure": 1006,
            "humidity": 66,
            "dew_point": 23.53,
            "clouds": 94,
            "wind_speed": 3.92,
            "wind_deg": 326,
            "weather": [
                {
                    "id": 804,
                    "main": "Clouds",
                    "description": "overcast clouds",
                    "icon": "04d"
                }
            ]
        }
    ]
}