{
    "lat": 3.033,
    "lon": 101.45,
    "timezone": "Asia/Kuala_Lumpur",
    "timezone_offset": 28800,
    "data": [
        {
            "dt": 1702868400,
            "sunrise": 1702854727,
            "sunset": 1702897732,
            "temp": 29.47,
            "feels_like": 35.59,
            "pressure": 1012,
            "humidity": 78,
            "dew_point": 25.23,
            "clouds": 20,
            "visibility": 9000,
            "wind_speed": 2.06,
            "wind_deg": 290,
            "weather": [
                {
                    "id": 500,
                    "main": "Rain",
                    "description": "light rain",
                    "icon": "10d"
                }
            ],
            "rain": {
                "1h": 0.13
            }
        }
    ]
}