{
    "lat": 3.033,
    "lon": 101.45,
    "timezone": "Asia/Kuala_Lumpur",
    "timezone_offset": 28800,
    "data": [
        {
            "dt": 1719039600,
            "sunrise": 1719011237,
            "sunset": 1719055503,
            "temp": 29.07,
            "feels_like": 31.31,
            "pressure": 1008,
            "humidity": 61,
            "dew_point": 20.78,
            "clouds": 20,
            "visibility": 10000,
            "wind_speed": 5.14,
            "wind_deg": 140,
            "weather": [
                {
                    "id": 801,
                    "main": "Clouds",
                    "description": "few clouds",
                    "icon": "02d"
                }
            ]
        }
    ]
}