{
    "lat": 3.033,
    "lon": 101.45,
    "timezone": "Asia/Kuala_Lumpur",
    "timezone_offset": 28800,
    "data": [
        {
            "dt": 1706288400,
            "sunrise": 1706311633,
            "sunset": 1706354762,
            "temp": 26.68,
            "feels_like": 29.84,
            "pressure": 1015,
            "humidity": 90,
            "dew_point": 24.9,
            "clouds": 98,
            "wind_speed": 1.55,
            "wind_deg": 108,
            "weather": [
                {
                    "id": 804,
                    "main": "Clouds",
                    "description": "overcast clouds",
                    "icon": "04n"
                }
            ]
        }
    ]
}