{
    "lat": 3.033,
    "lon": 101.45,
    "timezone": "Asia/Kuala_Lumpur",
    "timezone_offset": 28800,
    "data": [
        {
            "dt": 1737882000,
            "sunrise": 1737847630,
            "sunset": 1737890757,
            "temp": 27.91,
            "feels_like": 30.49,
            "pressure": 1007,
            "humidity": 70,
            "dew_point": 21.93,
            "clouds": 20,
            "visibility": 10000,
            "wind_speed": 2.06,
            "wind_deg": 300,
            "weather": [
                {
                    "id": 801,
                    "main": "Clouds",
                    "description": "few clouds",
                    "icon": "02d"
                }
            ]
        }
    ]
}