{
    "lat": 3.033,
    "lon": 101.45,
    "timezone": "Asia/Kuala_Lumpur",
    "timezone_offset": 28800,
    "data": [
        {
            "dt": 1744610400,
            "sunrise": 1744585736,
            "sunset": 1744629581,
            "temp": 33.95,
            "feels_like": 40.95,
            "pressure": 1009,
            "humidity": 95,
            "dew_point": 33.03,
            "clouds": 20,
            "visibility": 10000,
            "wind_speed": 1.54,
            "wind_deg": 0,
            "weather": [
                {
                    "id": 801,
                    "main": "Clouds",
                    "description": "few clouds",
                    "icon": "02d"
                }
            ]
        }
    ]
}