{
    "lat": 3.033,
    "lon": 101.45,
    "timezone": "Asia/Kuala_Lumpur",
    "timezone_offset": 28800,
    "data": [
        {
            "dt": 1710648000,
            "sunrise": 1710631171,
            "sunset": 1710674737,
            "temp": 31.92,
            "feels_like": 36.3,
            "pressure": 1012,
            "humidity": 58,
            "dew_point": 22.63,
            "clouds": 20,
            "visibility": 10000,
            "wind_speed": 1.03,
            "wind_deg": 0,
            "weather": [
                {
                    "id": 801,
                    "main": "Clouds",
                    "description": "few clouds",
                    "icon": "02d"
                }
            ]
        }
    ]
}