{
    "lat": 3.033,
    "lon": 101.45,
    "timezone": "Asia/Kuala_Lumpur",
    "timezone_offset": 28800,
    "data": [
        {
            "dt": 1719817200,
            "sunrise": 1719788947,
            "sunset": 1719833203,
            "temp": 31.03,
            "feels_like": 33.72,
            "pressure": 1008,
            "humidity": 55,
            "dew_point": 20.93,
            "clouds": 20,
            "visibility": 10000,
            "wind_speed": 2.06,
            "wind_deg": 250,
            "weather": [
                {
                    "id": 801,
                    "main": "Clouds",
                    "description": "few clouds",
                    "icon": "02d"
                }
            ]
        }
    ]
}