{
    "lat": 3.033,
    "lon": 101.45,
    "timezone": "Asia/Kuala_Lumpur",
    "timezone_offset": 28800,
    "data": [
        {
            "dt": 1723442400,
            "sunrise": 1723417958,
            "sunset": 1723461960,
            "temp": 33.19,
            "feels_like": 38.25,
            "pressure": 1008,
            "humidity": 55,
            "dew_point": 22.93,
            "clouds": 20,
            "visibility": 10000,
            "wind_speed": 2.57,
            "wind_deg": 0,
            "weather": [
                {
                    "id": 801,
                    "main": "Clouds",
                    "description": "few clouds",
                    "icon": "02d"
                }
            ]
        }
    ]
}